proyectov2/__init__.py
proyectov2/acciones/__init__.py
proyectov2/acciones/webserver.py
proyectov2/main.py
proyectov2-0.1.3.dist-info/entry_points.txt
proyectov2-0.1.3.dist-info/WHEEL
proyectov2-0.1.3.dist-info/METADATA
proyectov2-0.1.3.dist-info/RECORD
